nonblocking_stream_queue/__init__.py
nonblocking_stream_queue/reader.py
nonblocking_stream_queue-0.1.4.dist-info/LICENSE
nonblocking_stream_queue-0.1.4.dist-info/METADATA
nonblocking_stream_queue-0.1.4.dist-info/WHEEL
nonblocking_stream_queue-0.1.4.dist-info/top_level.txt
nonblocking_stream_queue-0.1.4.dist-info/RECORD
