Metadata-Version: 2.1
Name: nonblocking-stream-queue
Version: 0.1.4
Summary: Nonblocking stream reads using Queue and a pump thread
Project-URL: Homepage, https://github.com/xloem/nonblocking_stream_queue
Project-URL: Bug Tracker, https://github.com/xloem/nonblocking_stream_queue/issues
Classifier: Programming Language :: Python :: 3
Classifier: License :: Public Domain
Classifier: Operating System :: OS Independent
License-File: LICENSE
